RandomTesting/fulladder.v
module fullAdder(input A, input B, input C_in, output C_out, output Sum);

assign {C_out, Sum} = A + B + C_in;

endmodule

fulladder-test.v
module testbench;
reg A, B, C_in;
wire C_out, Sum;

fullAdder FAdd(.A(A), .B(B), .C_in(C_in), .C_out(C_out), .Sum(Sum));

    initial begin
        $dumpfile("gtkAdder.vcd");
        $dumpvars(0, testbench);
        $monitor($time, " ABC_in = %b%b%b, SUM = %b, C_out = %b", A, B, C_in, Sum, C_out);
        #5 A = 0; B = 0; C_in = 0;
        #5 C_in = 1;
        #5 B = 1; C_in = 0;
        #5 C_in = 1;
        #5 A = 1; B = 0; C_in = 0;
        #5 C_in = 1;
        #5 B = 1; C_in = 0;
        #5 C_in = 1;
        #5 $finish;
    end

endmodule

gtkAdder.vcd
$date
	Tue Jan  9 09:47:53 2024
$end
$version
	Icarus Verilog
$end
$timescale
	1s
$end
$scope module testbench $end
$var wire 1 ! Sum $end
$var wire 1 " C_out $end
$var reg 1 # A $end
$var reg 1 $ B $end
$var reg 1 % C_in $end
$scope module FAdd $end
$var wire 1 # A $end
$var wire 1 $ B $end
$var wire 1 % C_in $end
$var wire 1 ! Sum $end
$var wire 1 " C_out $end
$upscope $end
$upscope $end
$enddefinitions $end
$comment Show the parameter values. $end
$dumpall
$end
#0
$dumpvars
x%
x$
x#
x"
x!
$end
#5
0!
0"
0%
0$
0#
#10
1!
1%
#15
0%
1$
#20
0!
1"
1%
#25
0"
1!
0%
0$
1#
#30
0!
1"
1%
#35
0%
1$
#40
1!
1%
